key_registry/__init__.py
key_registry/registry.py
keyregistry-0.2.0.dist-info/METADATA
keyregistry-0.2.0.dist-info/WHEEL
keyregistry-0.2.0.dist-info/licenses/LICENSE
keyregistry-0.2.0.dist-info/RECORD
