Metadata-Version: 2.4
Name: KeyRegistry
Version: 0.2.0
Summary: A Python package for dynamic class registration and instantiation
Project-URL: Homepage, https://github.com/Mikyx-1/KeyRegistry
Project-URL: Repository, https://github.com/Mikyx-1/KeyRegistry
Project-URL: Issues, https://github.com/Mikyx-1/KeyRegistry/issues
Author-email: Le Hoang Viet <lehoangviet2k@gmail.com>
License:                                  Apache License
License-File: LICENSE
Classifier: License :: OSI Approved :: Apache Software License
Classifier: Operating System :: OS Independent
Classifier: Programming Language :: Python :: 3
Requires-Python: >=3.6
